LICENSE.txt
MANIFEST.in
README.md
setup.cfg
setup.py
oplra_reg.egg-info/PKG-INFO
oplra_reg.egg-info/SOURCES.txt
oplra_reg.egg-info/dependency_links.txt
oplra_reg.egg-info/entry_points.txt
oplra_reg.egg-info/requires.txt
oplra_reg.egg-info/top_level.txt
oplrareg/__init__.py
oplrareg/__main__.py
oplrareg/base.py
oplrareg/models.py
oplrareg/oplra_algorithms.py
oplrareg/solvers.py