Metadata-Version: 1.2
Name: oplra-reg
Version: 0.2
Summary: Mixed Integer Piecewise Linear Regression with Regularisation
Home-page: https://github.com/KISysBio/OPLRAreg
Author: Jonathan Cardoso Silva
Author-email: jonathan.car.silva@gmail.com
License: UNKNOWN
Platform: UNKNOWN
Classifier: Programming Language :: Python :: 3.5
Classifier: Programming Language :: Python :: 3.6
Requires-Python: >=3
